pymbtc/__init__.py
pymbtc/api.py
pymbtc/base.py
pymbtc/tradeapi.py
pymbtc-0.21.dist-info/LICENSE
pymbtc-0.21.dist-info/METADATA
pymbtc-0.21.dist-info/WHEEL
pymbtc-0.21.dist-info/top_level.txt
pymbtc-0.21.dist-info/RECORD
