Metadata-Version: 2.1
Name: pymbtc
Version: 0.21
Summary: API (dados e negociação) do Mercado Bitcoin
Home-page: http://github.com/lbltavares/pymbtc
Author: lbltavares
License: MIT
Platform: UNKNOWN
